<?xml version="1.0" encoding="utf-8" ?>
<dwsync>
<file name="phpmailer.lang-ar.php" server="www.devoladavoy.com.mx//www/" local="130257197908839968" remote="130168200600000000" Dst="2" />
<file name="phpmailer.lang-br.php" server="www.devoladavoy.com.mx//www/" local="130257197908889971" remote="130168200600000000" Dst="2" />
<file name="phpmailer.lang-ch.php" server="www.devoladavoy.com.mx//www/" local="130257197919340569" remote="130168200600000000" Dst="2" />
<file name="phpmailer.lang-cz.php" server="www.devoladavoy.com.mx//www/" local="130257197919380571" remote="130168200600000000" Dst="2" />
<file name="phpmailer.lang-ca.php" server="www.devoladavoy.com.mx//www/" local="130257197919420573" remote="130168200600000000" Dst="2" />
<file name="phpmailer.lang-de.php" server="www.devoladavoy.com.mx//www/" local="130257197930991235" remote="130168200600000000" Dst="2" />
<file name="phpmailer.lang-dk.php" server="www.devoladavoy.com.mx//www/" local="130257197931031237" remote="130168200600000000" Dst="2" />
<file name="phpmailer.lang-es.php" server="www.devoladavoy.com.mx//www/" local="130257197931081240" remote="130168200600000000" Dst="2" />
<file name="phpmailer.lang-et.php" server="www.devoladavoy.com.mx//www/" local="130257197942111871" remote="130168201200000000" Dst="2" />
<file name="phpmailer.lang-fi.php" server="www.devoladavoy.com.mx//www/" local="130257197942151873" remote="130168201200000000" Dst="2" />
<file name="phpmailer.lang-fo.php" server="www.devoladavoy.com.mx//www/" local="130257197942191876" remote="130168201200000000" Dst="2" />
<file name="phpmailer.lang-hu.php" server="www.devoladavoy.com.mx//www/" local="130257197950552354" remote="130168201200000000" Dst="2" />
<file name="phpmailer.lang-it.php" server="www.devoladavoy.com.mx//www/" local="130257197950582355" remote="130168201200000000" Dst="2" />
<file name="phpmailer.lang-fr.php" server="www.devoladavoy.com.mx//www/" local="130257197950702362" remote="130168201200000000" Dst="2" />
<file name="phpmailer.lang-ja.php" server="www.devoladavoy.com.mx//www/" local="130257197959652874" remote="130168201200000000" Dst="2" />
<file name="phpmailer.lang-nl.php" server="www.devoladavoy.com.mx//www/" local="130257197959692877" remote="130168201200000000" Dst="2" />
<file name="phpmailer.lang-no.php" server="www.devoladavoy.com.mx//www/" local="130257197959732879" remote="130168201200000000" Dst="2" />
<file name="phpmailer.lang-ro.php" server="www.devoladavoy.com.mx//www/" local="130257197967813341" remote="130168201200000000" Dst="2" />
<file name="phpmailer.lang-pl.php" server="www.devoladavoy.com.mx//www/" local="130257197967853343" remote="130168201200000000" Dst="2" />
<file name="phpmailer.lang-ru.php" server="www.devoladavoy.com.mx//www/" local="130257197967903346" remote="130168201200000000" Dst="2" />
<file name="phpmailer.lang-se.php" server="www.devoladavoy.com.mx//www/" local="130257197975953807" remote="130168201200000000" Dst="2" />
<file name="phpmailer.lang-tr.php" server="www.devoladavoy.com.mx//www/" local="130257197976063813" remote="130168201200000000" Dst="2" />
<file name="phpmailer.lang-zh.php" server="www.devoladavoy.com.mx//www/" local="130257197976113816" remote="130168201200000000" Dst="2" />
<file name="phpmailer.lang-zh_cn.php" server="www.devoladavoy.com.mx//www/" local="130257197984264282" remote="130168201200000000" Dst="2" />
</dwsync>